pyxi_azdo_http_client/__init__.py
pyxi_azdo_http_client/azdo_http_client.py
pyxi_azdo_http_client/azdo_url_builder.py
pyxi_azdo_http_client/http_client.py
pyxi_azdo_http_client/secret_provider.py
pyxi_azdo_http_client/url_builder.py
pyxi_azdo_http_client-0.0.9.dist-info/LICENSE
pyxi_azdo_http_client-0.0.9.dist-info/METADATA
pyxi_azdo_http_client-0.0.9.dist-info/WHEEL
pyxi_azdo_http_client-0.0.9.dist-info/top_level.txt
pyxi_azdo_http_client-0.0.9.dist-info/RECORD
