Metadata-Version: 2.1
Name: pyxi-azdo-http-client
Version: 0.0.9
Summary: A simple HTTP client for interacting with the AzureDevOps API.
Home-page: https://github.com/stiproot/py-azdo-http-client
Author: Simon Stipcich
Author-email: stipcich.simon@gmail.com
License: MIT
Keywords: python,package,azuredevops,beta
Classifier: Intended Audience :: Developers
Classifier: License :: OSI Approved :: MIT License
Classifier: Programming Language :: Python :: 3.11
License-File: LICENSE
Requires-Dist: environs
